{"slug":"38b-mos","title":"38b mos","bucket":"cbt_army","source_filename":"38b mos.docx","kind":"prose","question_count":0,"word_count":75,"qas":null,"prose":{"title":"38b mos","body":"The 38B MOS (Military Occupational Specialty) is a Civil Affairs Specialist in the U.S. Army. Civil Affairs Specialists act as a liaison between the military and civil authorities, local populations, and non-governmental organizations. They help plan and execute civil-military operations, conduct assessments, and provide support in areas such as governance, infrastructure, and public services. If you have any specific questions about the 38B MOS or need more information, feel free to ask!"}}