{"slug":"legal-and-privacy-issues-in-information-security","title":"Legal And Privacy Issues In Information Security","bucket":"cbt_security","source_filename":"Legal And Privacy Issues In Information Security.docx","kind":"qa","question_count":61,"word_count":759,"qas":[{"q":"Information","a":"An organizations most important asset"},{"q":"Information Security","a":"The study and practice of protecting information"},{"q":"Cryptography","a":"Practice of hiding information so unauthorized persons can't read it"},{"q":"Confidentiality","a":"Only people with the right permission can access and use information"},{"q":"Integrity","a":"Information systems and their data are correct"},{"q":"Availability","a":"The security goal of making information systems operate reliably."},{"q":"DoS","a":"Disrupts information systems so they're no longer available to users"},{"q":"User Domain","a":"Any users of an organizations IT system. AKA End users"},{"q":"Workstation Domain","a":"Computing devices used by end users"},{"q":"LAN Domain","a":"Organizations LAN technologies"},{"q":"WAN Domain","a":"Organizations with remote locations connect to this"},{"q":"Remote access Domain","a":"Process and procedures that end users use to access the organizations IT infrastructure and data."},{"q":"System/Application Domain","a":"Equipment and data an organization uses to support its' IT infrastructure."},{"q":"Separation of duties","a":"When 2 or more employees split critical task functions"},{"q":"Patch","a":"Software or code that updates a program to address security problems"},{"q":"Exploit","a":"Successful attacks against a vulnerability"},{"q":"Zero-Day Vulnerability","a":"Exploited before a patch is provided"},{"q":"Threat","a":"Anything that can harm an information system"},{"q":"Risk","a":"The likelihood that a threat will exploit a vulnerability and cause harm"},{"q":"Least privilege","a":"Systems run with the lowest amount of permissions needed to complete tasks."},{"q":"Need to know","a":"Allows access to only needed data"},{"q":"Logic bomb","a":"Lies dormant for a certain period and when conditions are met it carries out its malicious function."},{"q":"Industry sector","a":"Group of organizations that share a similar industry type."},{"q":"U.S. Freedom of Information Act","a":"Governs access to public records of the U.S. federal government"},{"q":"Tort","a":"Wrongful act or harm that hurts a person"},{"q":"Defamation","a":"Maliciously saying false things about another person"},{"q":"Web Beacon","a":"Small, invisible electronic file that is placed on a web page or in an e-mail message that monitors behavior"},{"q":"Preemption","a":"The legal concept that means a higher-ranking law will exclude a lower-ranking law on the same subject"},{"q":"Federalism","a":"Describes the relationship between the states and the U.S. federal government."},{"q":"Civil procedure","a":"Claims between individuals"},{"q":"Criminal procedure","a":"Wrongs against society"},{"q":"Compliance","a":"The action of following applicable laws and rules and regulations"},{"q":"Audit","a":"An evaluation and verification that certain objectives are met"},{"q":"The Bank Secrecy Act/Currency and Foreign Transactions Reporting Act","a":"Congress created this law to fight drug trafficking, money laundering, and other crimes."},{"q":"The Gramm-Leach-Bliley Act","a":"Defines any financial institution as any institution that conducts financial activities."},{"q":"The Federal Reserve (The Fed)","a":"Central bank of the U.S., reports directly to Congress."},{"q":"The Federal Deposit Insurance Corporation","a":"Provides deposit insurance to banks"},{"q":"The Fair Credit Reporting Act","a":"Allows consumers to opt out of some types of information sharing"},{"q":"Pretexting","a":"Attempt to gain access to customer information without proper authority to do so"},{"q":"The Childrens Online Privacy Act","a":"Governs how information from children is to be collected and used"},{"q":"The Childrens Internet Protection Act","a":"Protects minors from obscene or objectionable material on school or library computers"},{"q":"The Family Educational Rights and Privacy Act","a":"Protects the privacy rights of students and their educational records"},{"q":"Health Insurance Portability and Accountability Act (HIPAA)","a":"Fights health insurance fraud, simplifies how health insurance is administered."},{"q":"Office for Civil Rights","a":"Enforces HIPAA Privacy and Security Rules"},{"q":"The Sarbanes-Oxley Act","a":"Protects shareholders and investors from financial fraud."},{"q":"ISO/IEC 27002","a":"Lists 14 sections of information security safeguards."},{"q":"National Institute of Standards and Technology (NIST)","a":"Creates information security guidance for federal agencies."},{"q":"Federal Information Security Management Act (FISMA)","a":"Protects federal IT systems and the data in those systems"},{"q":"Category 0","a":"Exercise/Network testing. Internal network testing"},{"q":"Category 1","a":"Unauthorized access. Must be reported to their IT systems even if data is not compromised"},{"q":"Category 2","a":"Denial of Service. Must report successful attacks that harm IT systems"},{"q":"Category 3","a":"Malicious Code. Must report successful installation of software."},{"q":"Category 4","a":"Improper use. Must report violations of their acceptable use policies."},{"q":"Category 5","a":"Scans, probes, and Attempted Access. Must report any activities that seek to access or identify IT systems."},{"q":"Category 6","a":"Investigation. Unusual events that require more review due to being odd or potentially harmful."},{"q":"Must be protected per PCI DSS requirements","a":"An e-commerce Web server"},{"q":"Fair and Accurate Transaction Act","a":"Enacted by Congress in response to growth in identity theft crime"},{"q":"Main goal of information security","a":"CIA"},{"q":"U.S. Supreme Court justices","a":"Are nominated by the president"},{"q":"The U.S. Cabinet consists of","a":"The vice president and the heads of the 15 executive departments"},{"q":"Source of legal authority for the U.S government","a":"The U.S. Constitution"}],"prose":null}