{"slug":"drivers-of-placard-vehicles-transporting-hazardous-materials-must-stop","question":"Drivers of placard vehicles transporting hazardous materials must stop ___ to ___ feet from the nearest rail of a railroad","canonical_answer":"15 to 50 ft","appears_in_count":8,"appears_in":[{"slug":"cdl-hazmat-practice-test","title":"Cdl Hazmat Practice Test","bucket":"cbt_health","answer":"15 to 50 ft"},{"slug":"hazmat-practice","title":"Hazmat Practice","bucket":"cbt_health","answer":"15 to 50 ft"},{"slug":"hazmat-practice-tests","title":"Hazmat Practice Tests","bucket":"cbt_health","answer":"15 to 50 ft"},{"slug":"hazmat-pratice-test","title":"Hazmat Pratice Test","bucket":"cbt_health","answer":"15 to 50 ft"},{"slug":"hazmat-pre-test","title":"Hazmat Pre Test","bucket":"cbt_health","answer":"15 to 50 ft"},{"slug":"hazmat-test-answers-2021","title":"Hazmat Test Answers 2021","bucket":"cbt_health","answer":"15 to 50 ft"},{"slug":"practice-test-for-hazmat","title":"Practice Test For Hazmat","bucket":"cbt_health","answer":"15 to 50 ft"},{"slug":"practice-test-hazmat","title":"Practice Test Hazmat","bucket":"cbt_health","answer":"15 to 50 ft"}]}