{"slug":"name-one-patients-rights-under-hipaa","question":"Name one patients' rights under HIPAA:","canonical_answer":"The right to request that communications from the facility be kept confidential.","appears_in_count":6,"appears_in":[{"slug":"hipaa-answers","title":"Hipaa Answers","bucket":"cbt_health","answer":"The right to request that communications from the facility be kept confidential."},{"slug":"hipaa-compliance-test","title":"Hipaa Compliance Test","bucket":"cbt_health","answer":"The right to request that communications from the facility be kept confidential."},{"slug":"hipaa-practice-test","title":"Hipaa Practice Test","bucket":"cbt_health","answer":"The right to request that communications from the facility be kept confidential."},{"slug":"hipaa-questions-and-answer-test","title":"Hipaa Questions And Answer Test","bucket":"cbt_health","answer":"The right to request that communications from the facility be kept confidential."},{"slug":"hipaa-quiz-questions","title":"Hipaa Quiz Questions","bucket":"cbt_health","answer":"The right to request that communications from the facility be kept confidential."},{"slug":"hipaa-test-questions","title":"Hipaa Test Questions","bucket":"cbt_health","answer":"The right to request that communications from the facility be kept confidential."}]}