{"slug":"technological-advances-select-all-that-apply","question":"Technological advances ______________________________. Select all that apply.","canonical_answer":"Increase risk of information loss\n\nAllow insiders to access more data","appears_in_count":5,"appears_in":[{"slug":"dod-insider-threat-training","title":"Dod Insider Threat Training","bucket":"cbt_annual","answer":"Increase risk of information loss\n\nAllow insiders to access more data"},{"slug":"elicitation-scenario-insider-threat","title":"Elicitation Scenario Insider Threat","bucket":"cbt_annual","answer":"Increase risk of information loss\n\nAllow insiders to access more data"},{"slug":"insider-threat-awareness-hotspots","title":"Insider Threat Awareness Hotspots","bucket":"cbt_annual","answer":"Increase risk of information loss\n\nAllow insiders to access more data"},{"slug":"insider-threat-awareness-phishing-scenario","title":"Insider Threat Awareness Phishing Scenario","bucket":"cbt_annual","answer":"Increase risk of information loss\n\nAllow insiders to access more data"},{"slug":"insider-threat-awareness-test","title":"Insider Threat Awareness Test","bucket":"cbt_annual","answer":"Increase risk of information loss\n\nAllow insiders to access more data"}]}