{"slug":"what-action-should-you-take-if-you-discover-your-hazardous-materials-s","question":"What action should you take if you discover your hazardous materials shipment leaking at a rest stop but there is no phone available?\n1) Leave your truck parked with its emergency lights on and walk for help.\n2) Keep driving for help as quickly as possible.\n3) Keep driving slowly and cautiously until you reach a phone.\n4) Send someone for help with all the necessary information.","canonical_answer":"Send someone for help with all the necessary information.","appears_in_count":5,"appears_in":[{"slug":"hazmat-endorsement-nj","title":"Hazmat Endorsement Nj","bucket":"cbt_health","answer":"Send someone for help with all the necessary information."},{"slug":"hazmat-practice-test-nj","title":"Hazmat Practice Test Nj","bucket":"cbt_health","answer":"Send someone for help with all the necessary information."},{"slug":"hazmat-test-nj","title":"Hazmat Test Nj","bucket":"cbt_health","answer":"Send someone for help with all the necessary information."},{"slug":"nj-hazmat-practice-test","title":"Nj Hazmat Practice Test","bucket":"cbt_health","answer":"Send someone for help with all the necessary information."},{"slug":"nj-hazmat-test-answers","title":"Nj Hazmat Test Answers","bucket":"cbt_health","answer":"Send someone for help with all the necessary information."}]}