{"slug":"who-might-be-interested-in-non-public-information-that-an-insider-can-","question":"Who might be interested in non-public information that an insider can provide? Select all that apply.","canonical_answer":"Terrorist organizations\n\nNon-state actors\n\nForeign governments\n\nCompetitors\n\n(select all 4 answers)","appears_in_count":8,"appears_in":[{"slug":"dod-insider-threat","title":"Dod Insider Threat","bucket":"cbt_annual","answer":"Non-state actors, Terrorist organizations, foreign governments and competitors"},{"slug":"dod-insider-threat-training","title":"Dod Insider Threat Training","bucket":"cbt_annual","answer":"Competitors\n\nNon-state actors\n\nTerrorist organizations\n\nForeign governments"},{"slug":"elicitation-scenario-insider-threat","title":"Elicitation Scenario Insider Threat","bucket":"cbt_annual","answer":"Competitors\n\nNon-state actors\n\nTerrorist organizations\n\nForeign governments"},{"slug":"insider-threat-awareness-hotspots","title":"Insider Threat Awareness Hotspots","bucket":"cbt_annual","answer":"Competitors\n\nNon-state actors\n\nTerrorist organizations\n\nForeign governments"},{"slug":"insider-threat-awareness-phishing-scenario","title":"Insider Threat Awareness Phishing Scenario","bucket":"cbt_annual","answer":"Competitors\n\nNon-state actors\n\nTerrorist organizations\n\nForeign governments"},{"slug":"insider-threat-awareness-test","title":"Insider Threat Awareness Test","bucket":"cbt_annual","answer":"Competitors\n\nNon-state actors\n\nTerrorist organizations\n\nForeign governments"},{"slug":"list-three-thresholds-for-insider-threat","title":"List Three Thresholds For Insider Threat","bucket":"cbt_annual","answer":"-Competitors\n-Terrorist organizations\n-Foreign governments\n-Non-state actors"},{"slug":"preconditions-for-an-insider-threat","title":"Preconditions For An Insider Threat","bucket":"cbt_annual","answer":"Terrorist organizations\n\nNon-state actors\n\nForeign governments\n\nCompetitors\n\n(select all 4 answers)"}]}