{"slug":"you-should-never-transport-a-package-labeled-poison-if-you-are-hauling","question":"You should never transport a package labeled poison if you are hauling...","canonical_answer":"food products","appears_in_count":9,"appears_in":[{"slug":"cdl-hazmat-practice-test","title":"Cdl Hazmat Practice Test","bucket":"cbt_health","answer":"food products"},{"slug":"cdl-hazmat-test","title":"Cdl Hazmat Test","bucket":"cbt_health","answer":"Food products"},{"slug":"hazmat-practice","title":"Hazmat Practice","bucket":"cbt_health","answer":"food products"},{"slug":"hazmat-practice-tests","title":"Hazmat Practice Tests","bucket":"cbt_health","answer":"food products"},{"slug":"hazmat-pratice-test","title":"Hazmat Pratice Test","bucket":"cbt_health","answer":"food products"},{"slug":"hazmat-pre-test","title":"Hazmat Pre Test","bucket":"cbt_health","answer":"food products"},{"slug":"hazmat-test-answers-2021","title":"Hazmat Test Answers 2021","bucket":"cbt_health","answer":"food products"},{"slug":"practice-test-for-hazmat","title":"Practice Test For Hazmat","bucket":"cbt_health","answer":"food products"},{"slug":"practice-test-hazmat","title":"Practice Test Hazmat","bucket":"cbt_health","answer":"food products"}]}